MANIFEST.in
README.md
requirements.txt
setup.py
src/sshstdlib/__init__.py
src/sshstdlib/client.py
src/sshstdlib/client_test.py
src/sshstdlib/exec_channel.py
src/sshstdlib/library.py
src/sshstdlib/remote.py
src/sshstdlib/remote_client.py
src/sshstdlib/remote_test.py
src/sshstdlib/sshos.py
src/sshstdlib/sshos_test.py
src/sshstdlib/sshshutil.py
src/sshstdlib/sshshutil_test.py
src/sshstdlib/sshsubprocess.py
src/sshstdlib/sshsubprocess_test.py
src/sshstdlib/sshtempfile.py
src/sshstdlib/sshtempfile_test.py
src/sshstdlib/sshurllib2.py
src/sshstdlib/testcommon.py
src/sshstdlib.egg-info/PKG-INFO
src/sshstdlib.egg-info/SOURCES.txt
src/sshstdlib.egg-info/dependency_links.txt
src/sshstdlib.egg-info/requires.txt
src/sshstdlib.egg-info/top_level.txt