Metadata-Version: 1.1
Name: sshstdlib
Version: 1.4
Summary: A standard library emulation layer over SSH
Home-page: http://github.com/stestagg/sshstdlib
Author: Steve Stagg
Author-email: stestagg@gmail.com
License: BSD
Platform: UNKNOWN
Classifier: Development Status :: 4 - Beta
Classifier: Intended Audience :: Developers
Classifier: License :: OSI Approved :: BSD License
Classifier: Operating System :: OS Independent
Classifier: Programming Language :: Python
